py50_statannotations/Annotation.py
py50_statannotations/Annotator.py
py50_statannotations/PValueFormat.py
py50_statannotations/_GroupsPositions.py
py50_statannotations/_Plotter.py
py50_statannotations/__init__.py
py50_statannotations/_version.py
py50_statannotations/format_annotations.py
py50_statannotations/stats/ComparisonsCorrection.py
py50_statannotations/stats/README.rst
py50_statannotations/stats/StatResult.py
py50_statannotations/stats/StatTest.py
py50_statannotations/stats/__init__.py
py50_statannotations/stats/test.py
py50_statannotations/stats/utils.py
py50_statannotations/utils.py
py50_statannotations-0.0.1.dist-info/LICENSE
py50_statannotations-0.0.1.dist-info/METADATA
py50_statannotations-0.0.1.dist-info/WHEEL
py50_statannotations-0.0.1.dist-info/RECORD
