Metadata-Version: 2.1
Name: py50-statannotations
Version: 0.0.1
Summary: A fork of statannotations for use with py50-streamlit application
License: MIT
Author: Tony E. Lin
Author-email: tonyelin@tmu.edu
Requires-Python: >=3.9,<4.0
Classifier: License :: OSI Approved :: MIT License
Classifier: Programming Language :: Python :: 3
Classifier: Programming Language :: Python :: 3.9
Classifier: Programming Language :: Python :: 3.10
Classifier: Programming Language :: Python :: 3.11
Classifier: Programming Language :: Python :: 3.12
Requires-Dist: matplotlib (>=2.2.2)
Requires-Dist: numpy (>=1.12.1)
Requires-Dist: packaging (>=20)
Requires-Dist: pandas (>=0.23.0,<2.0.0)
Requires-Dist: scipy (>=1.1.0)
Requires-Dist: seaborn (==0.12.2)
Requires-Dist: statsmodels (>0.14)
